Bytebin/Bytebin.py
Bytebin/__init__.py
Bytebin-0.0.2.dist-info/METADATA
Bytebin-0.0.2.dist-info/WHEEL
Bytebin-0.0.2.dist-info/top_level.txt
Bytebin-0.0.2.dist-info/RECORD
