Metadata-Version: 2.1
Name: Bytebin
Version: 0.0.2
Summary: Bytebin API Wrapper
Home-page: https://github.com/alexraskin/bytebin.py
Author: alexraskin
Author-email: <root@alexraskin.com
License: MIT License
Keywords: module,Bytebin,library,package,python
Classifier: Programming Language :: Python
Classifier: Programming Language :: Python :: 3
Classifier: Programming Language :: Python :: 3.5
Classifier: Programming Language :: Python :: 3.6
Classifier: Programming Language :: Python :: 3.7
Classifier: Programming Language :: Python :: 3.8
Classifier: Programming Language :: Python :: 3.9
Classifier: Programming Language :: Python :: 3.10
Requires-Dist: requests
